{"cameraMode":{"drawMode":0,"name":"Shaded","section":"Shading Mode"},"sceneLighting":true,"audioPlay":false,"sceneViewState":{"m_AlwaysRefresh":false,"showFog":true,"showSkybox":true,"showFlares":true,"showImageEffects":true,"showParticleSystems":true,"showVisualEffectGraphs":true,"m_FxEnabled":true},"in2DMode":false,"pivot":{"x":0.02307833544909954,"y":3.1179916858673097,"z":2.812894344329834},"rotation":{"x":0.019188925623893739,"y":-0.00839973147958517,"z":-0.00016497056640218943,"w":-0.9997891783714294},"size":11.189308166503907,"orthographic":false}